{
  "project_info": {
    "project_number": "570014568272",
    "project_id": "solora-e00a4",
    "storage_bucket": "solora-e00a4.firebasestorage.app"
  },
  "client": [
    {
      "client_info": {
        "mobilesdk_app_id": "1:570014568272:android:1f0dfc9c63c25ce1ce2655",
        "android_client_info": {
          "package_name": "dev.solora"
        }
      },
      "oauth_client": [
        {
          "client_id": "570014568272-3hul7i6rpmsqp7dauf166ek5jdeu8lrr.apps.googleusercontent.com",
          "client_type": 1,
          "android_info": {
            "package_name": "dev.solora",
            "certificate_hash": "895c75c408027e0cf2407bad20b6df097fc6be3a"
          }
        },
        {
          "client_id": "570014568272-gd86hu4qi23o92k6ji98ii5g26t97ks2.apps.googleusercontent.com",
          "client_type": 3
        }
      ],
      "api_key": [
        {
          "current_key": "AIzaSyCAfU_ngJElc7SNXMpH2r2yq5rUsPcxrZc"
        }
      ],
      "services": {
        "appinvite_service": {
          "other_platform_oauth_client": [
            {
              "client_id": "570014568272-gd86hu4qi23o92k6ji98ii5g26t97ks2.apps.googleusercontent.com",
              "client_type": 3
            }
          ]
        }
      }
    }
  ],
  "configuration_version": "1"
}